openai_python_client/__init__.py
openai_python_client/client.py
openai_python_client/errors.py
openai_python_client/py.typed
openai_python_client/types.py
openai_python_client/api/__init__.py
openai_python_client/api/assistants/__init__.py
openai_python_client/api/assistants/cancel_run.py
openai_python_client/api/assistants/create_assistant.py
openai_python_client/api/assistants/create_message.py
openai_python_client/api/assistants/create_run.py
openai_python_client/api/assistants/create_thread.py
openai_python_client/api/assistants/create_thread_and_run.py
openai_python_client/api/assistants/delete_assistant.py
openai_python_client/api/assistants/delete_message.py
openai_python_client/api/assistants/delete_thread.py
openai_python_client/api/assistants/get_assistant.py
openai_python_client/api/assistants/get_message.py
openai_python_client/api/assistants/get_run.py
openai_python_client/api/assistants/get_run_step.py
openai_python_client/api/assistants/get_thread.py
openai_python_client/api/assistants/list_assistants.py
openai_python_client/api/assistants/list_messages.py
openai_python_client/api/assistants/list_run_steps.py
openai_python_client/api/assistants/list_runs.py
openai_python_client/api/assistants/modify_assistant.py
openai_python_client/api/assistants/modify_message.py
openai_python_client/api/assistants/modify_run.py
openai_python_client/api/assistants/modify_thread.py
openai_python_client/api/assistants/submit_tool_ouputs_to_run.py
openai_python_client/api/audio/__init__.py
openai_python_client/api/audio/create_speech.py
openai_python_client/api/audio/create_transcription.py
openai_python_client/api/audio/create_translation.py
openai_python_client/api/batch/__init__.py
openai_python_client/api/batch/cancel_batch.py
openai_python_client/api/batch/create_batch.py
openai_python_client/api/batch/list_batches.py
openai_python_client/api/batch/retrieve_batch.py
openai_python_client/api/chat/__init__.py
openai_python_client/api/chat/create_chat_completion.py
OpenAI_Python_Client-0.2.3.dist-info/METADATA
OpenAI_Python_Client-0.2.3.dist-info/WHEEL
OpenAI_Python_Client-0.2.3.dist-info/top_level.txt
OpenAI_Python_Client-0.2.3.dist-info/RECORD
