Metadata-Version: 2.1
Name: OpenAI-Python-Client
Version: 0.2.3
Summary: A pure-python implementation built from OpenAPI-Python-Client Generator https://github.com/openapi-generators/openapi-python-client and OpenAI's published OpenAPI spec https://github.com/openai/openai-openapi
Author-email: Ian Goforth <ian.goforth@gmail.com>
License: MIT
Requires-Python: >=3.11
Requires-Dist: httpx >=0.27.0
Requires-Dist: attrs >=23.2.0
Requires-Dist: python-dateutil >=2.9.0.post0
